{
    "metadata": {
        "width": 1920,
        "height": 1080,
        "fps": 29.97002997002997
    },
    "index": {
        "person_only": {
            "presence": [
                [ 4733, 9139 ], [ 11971, 15383 ], [ 18690, 20656 ]
            ]
        },
        "car_person_only": {
            "presence": [
                [ 3456, 4732 ], [ 9140, 11970 ], [ 15384, 18689 ]
            ]
        },
        "car_only": {
            "presence": [
                [ 1, 3455 ]
            ]
        },
    }
}